Workbook

Sheet CABAC Fiduciary 2025
A2: COMPARATIVE APPROVED BUDGET and ACTUAL COLLECTION
A3: INTERNALLY GENERATED FUNDS (IGF) - Fiduciary Fees
A5: CY 2025
A6: EVSU ORMOC CAMPUS | V6: Page 1 of 7
E7: Approved | G7: A L L O T M E N T
E8: Budget | F8: Total | G8: (ACTUAL COLLECTION)
A9: PROGRAM / ACTIVITY | D9: Fiduciary | E9: (Based on | F9: Available | J9: FHE
D10: Fees | E10: Estimated | F10: Allotment | G10: Jan | H10: Feb | I10: March | J10: 41334 | K10: Apr | L10: May | M10: June | N10: July | O10: August | P10: Sept | Q10: Oct | R10: FHE | S10: Nov | T10: Nov | U10: Dec | V10: Balance
E11: Collection) | J11: 2025 | R11: SS 2024-2025 | Z11: =X11+X12 -> 0
A12: I. | B12: Personnel Services (PS)
B13: Honoraria - Overload | D13: Laboratory | E13: 2000000 | F13: =SUM(G13:U13) -> 2000000 | J13: 2000000 | V13: =E13-F13 -> 0
V14: =E14-F14 -> 0
B15: Honoraria - Part-time | D15: Laboratory | E15: 3000000 | F15: =SUM(G15:U15) -> 1082651 | J15: 1082651 | V15: =E15-F15 -> 1917349
D16: Development Fee | E16: 2000000 | F16: =SUM(G16:U16) -> 2000000 | J16: 2000000 | V16: =E16-F16 -> 0
D17: Computer Fee | E17: 361755 | F17: =SUM(G17:U17) -> 313585.15 | J17: 313585.15 | V17: =E17-F17 -> 48169.85
V18: =E18-F18 -> 0
B19: Honoraria | D19: NSTP | E19: 400000 | F19: =SUM(G19:U19) -> 196781.93 | J19: =125150+10000+26000+11631.93+24000 -> 196781.93 | V19: =E19-F19 -> 203218.07
D20: Athletic | E20: 173468.66 | F20: =SUM(G20:U20) -> 99503.1 | G20: 900 | J20: =76.66+98526.44 -> 98603.1 | V20: =E20-F20 -> 73965.56
D21: Cultural | E21: 100000 | F21: =SUM(G21:U21) -> 100 | M21: 100 | V21: =E21-F21 -> 99900
D22: Computer/ Internet | F22: =SUM(G22:U22) -> 0 | V22: =E22-F22 -> 0
D23: Dev Fee | F23: =SUM(G23:U23) -> 0 | V23: =E23-F23 -> 0
D24: Grad School | F24: =SUM(G24:U24) -> 0 | V24: =E24-F24 -> 0
D25: SLD | F25: =SUM(G25:U25) -> 0 | V25: =E25-F25 -> 0
D26: Senior High | F26: =SUM(G26:U26) -> 0 | V26: =E26-F26 -> 0
D27: School Organ Fee | F27: =SUM(G27:U27) -> 0 | V27: =E27-F27 -> 0
D28: Guidance | E28: 5000 | F28: =SUM(G28:U28) -> 0 | V28: =E28-F28 -> 5000
D29: Compre Exam | F29: =SUM(G29:U29) -> 0 | V29: =E29-F29 -> 0
D30: GS/Defense fee | F30: =SUM(G30:U30) -> 0 | V30: =E30-F30 -> 0
D31: Petition | F31: =SUM(G31:U31) -> 186834 | G31: =5050+4200+91180 -> 100430 | H31: =16364+70040 -> 86404 | V31: =E31-F31 -> -186834
D32: OJT/Practicum | E32: 321600 | F32: =SUM(G32:U32) -> 208500 | G32: =26500+4000+110000+68000 -> 208500 | V32: =E32-F32 -> 113100
E33: =SUM(E13:E32) -> 8361823.7 | F33: =SUM(F13:F32) -> 6087955.1 | G33: =SUM(G19:G32) -> 309830 | H33: =SUM(H19:H32) -> 86404 | I33: =SUM(I19:I32) -> 0 | J33: =SUM(J13:J32) -> 5691621.1 | K33: =SUM(K19:K32) -> 0 | L33: =SUM(L19:L32) -> 0 | M33: =SUM(M19:M32) -> 100 | N33: =SUM(N19:N32) -> 0 | O33: =SUM(O19:O32) -> 0 | P33: =SUM(P19:P32) -> 0 | Q33: =SUM(Q19:Q32) -> 0 | R33: =SUM(R19:R32) -> 0 | ... U33: =SUM(U19:U32) -> 0 | V33: =SUM(V13:V32) -> 2273868.5
A34: II. | B34: Maintenance and Other
B35: Operating Expenses
B36: (MOOE)
B37: Traveling Expenses | D37: NSTP | E37: 59000 | F37: =SUM(G37:U37) -> 59000 | J37: 59000 | V37: =E37-F37 -> 0
D38: Athletics | E38: 364436.8 | F38: =SUM(G38:U38) -> 364436.8 | J38: 364436.8 | V38: =E38-F38 -> 0
D39: SCUAA | E39: 147240 | F39: =SUM(G39:U39) -> 180876.64 | G39: 90000 | J39: 87996.64 | M39: =2880 -> 2880 | V39: =E39-F39 -> -33636.64
D40: Comp Fee | E40: 300000 | F40: =SUM(G40:U40) -> 194368.72 | J40: 194368.72 | V40: =E40-F40 -> 105631.28
D41: Cultural | E41: 217414.54 | F41: =SUM(G41:U41) -> 218314.54 | G41: 900 | J41: 217414.54 | V41: =E41-F41 -> -900
D42: Dev Fee | E42: 150000 | F42: =SUM(G42:U42) -> 3000 | G42: 3000 | V42: =E42-F42 -> 147000
D43: Grad School | F43: =SUM(G43:U43) -> 0 | V43: =E43-F43 -> 0
D44: Sec Lab Schl | F44: =SUM(G44:U44) -> 0 | V44: =E44-F44 -> 0
D45: SAF | E45: 22471.51 | F45: =SUM(G45:U45) -> 22471 | J45: 22471 | V45: =E45-F45 -> 0.51 | Z45: =X45+X46+X48+X49+X50+X51+X52+X54+X55 -> 0
D46: SCF | E46: 60000 | F46: =SUM(G46:U46) -> 69900 | G46: 300 | J46: 60000 | M46: 9600 | V46: =E46-F46 -> -9900
D47: SCF -SLD | F47: =SUM(G47:U47) -> 0 | V47: =E47-F47 -> 0
D48: SOF | E48: 53800 | F48: =SUM(G48:U48) -> 73600 | G48: 600 | J48: 53800 | M48: 19200 | V48: =E48-F48 -> -19800
D49: Guidance | E49: 100000 | F49: =SUM(G49:U49) -> 5940 | G49: 180 | M49: 5760 | V49: =E49-F49 -> 94060
D50: Laboratory | E50: 100000 | F50: =SUM(G50:U50) -> 0 | V50: =E50-F50 -> 100000
D51: Library | E51: 50000 | F51: =SUM(G51:U51) -> 50900 | G51: 900 | J51: 50000 | V51: =E51-F51 -> -900
D52: Medical | E52: 60000 | F52: =SUM(G52:U52) -> 50600 | G52: 600 | J52: 50000 | V52: =E52-F52 -> 9400
D53: Dental | F53: =SUM(G53:U53) -> 0 | V53: =E53-F53 -> 0
D54: OJT fee | E54: 160800 | F54: =SUM(G54:U54) -> 0 | V54: =E54-F54 -> 160800
E55: =SUM(E37:E54) -> 1845162.9 | F55: =SUM(F37:F54) -> 1293407.7 | G55: =SUM(G37:G54) -> 96480 | H55: =SUM(H37:H54) -> 0 | I55: =SUM(I37:I54) -> 0 | J55: =SUM(J37:J54) -> 1159487.7 | K55: =SUM(K37:K54) -> 0 | L55: =SUM(L37:L54) -> 0 | ... V55: =SUM(V37:V54) -> 551755.15
B57: Traveling Expenses - Foreign | D57: Dev Fee | E57: 150000 | F57: =SUM(G57:U57) -> 0 | V57: =E57-F57 -> 150000
D58: Laboratory | F58: =SUM(G58:U58) -> 0 | V58: =E58-F58 -> 0
E59: =SUM(E57:E58) -> 150000 | G59: =G58+G57 -> 0 | H59: =H58+H57 -> 0 | I59: =I58+I57 -> 0 | J59: =J58+J57 -> 0 | K59: =K58+K57 -> 0 | L59: =L58+L57 -> 0 | M59: =M58+M57 -> 0 | N59: =N58+N57 -> 0 | O59: =O58+O57 -> 0 | P59: =SUM(P57:P58) -> 0 | Q59: =SUM(Q57:Q58) -> 0 | R59: =SUM(R57:R58) -> 0 | S59: =SUM(S57:S58) -> 0 | T59: =SUM(T57:T58) -> 0 | U59: =SUM(U57:U58) -> 0 | V59: =SUM(V57:V58) -> 150000
V60: =E60-F60 -> 0
A62: COMPARATIVE APPROVED BUDGET and ACTUAL COLLECTION
A63: INTERNALLY GENERATED FUNDS (IGF) - Fiduciary Fees
A64: .
A65: CY 2025
A66: EVSU ORMOC CAMPUS | V66: Page 1 of 7
E67: Approved | G67: A L L O T M E N T
E68: Budget | F68: Total | G68: (ACTUAL COLLECTION)
A69: PROGRAM / ACTIVITY | D69: Fiduciary | E69: (Based on | F69: Available | J69: FHE
D70: Fees | E70: Estimated | F70: Allotment | G70: Jan | H70: Feb | I70: March | J70: 41334 | K70: Apr | L70: May | M70: June | N70: July | O70: August | P70: Sept | Q70: Oct | R70: FHE | S70: Nov | T70: Nov | U70: Dec | V70: Balance
E71: Collection) | J71: 2025 | R71: SS 2023-2024 | Z71: =X71+#REF! -> #REF!
B72: Training Expenses | D72: NSTP | E72: 20000 | F72: =SUM(G72:U72) -> 20000 | J72: 20000 | V72: =E72-F72 -> 0
D73: Athletic | E73: 100000 | F73: =SUM(G73:U73) -> 0 | V73: =E73-F73 -> 100000
D74: Comp Fee | E74: 250000 | F74: =SUM(G74:U74) -> 0 | V74: =E74-F74 -> 250000
D75: Cultural Fee | E75: 100000 | F75: =SUM(G75:U75) -> 0 | V75: =E75-F75 -> 100000
D76: Dev Fee | E76: 10000 | F76: =SUM(G76:U76) -> 0 | V76: =E76-F76 -> 10000
D77: Grad Schl | F77: =SUM(G77:U77) -> 0 | V77: =E77-F77 -> 0
D78: Sec Lab Schl | F78: =SUM(G78:U78) -> 0 | V78: =E78-F78 -> 0
D79: Senior High | F79: =SUM(G79:U79) -> 0 | V79: =E79-F79 -> 0
D80: SAF | E80: 45610 | F80: =SUM(G80:U80) -> 45910 | G80: 300 | J80: 45610 | V80: =E80-F80 -> -300
D81: SCF | E81: 50000 | F81: =SUM(G81:U81) -> 50000 | J81: 50000 | V81: =E81-F81 -> 0
D82: Guidance | E82: 50000 | F82: =SUM(G82:U82) -> 0 | V82: =E82-F82 -> 50000
D83: SOF | E83: 145243.02 | F83: =SUM(G83:U83) -> 145243.02 | J83: 145243.02 | V83: =E83-F83 -> 0
D84: Journal Fee | F84: =SUM(G84:U84) -> 0 | V84: =E84-F84 -> 0
D85: Library | E85: 20000 | F85: =SUM(G85:U85) -> 20000 | J85: 20000 | V85: =E85-F85 -> 0
D86: Laboratory | F86: =SUM(G86:U86) -> 0 | V86: =E86-F86 -> 0
D87: Medical | E87: 30000 | F87: =SUM(G87:U87) -> 30000 | J87: 30000 | V87: =E87-F87 -> 0
D88: Dental | F88: =SUM(G88:U88) -> 0 | V88: =E88-F88 -> 0
E89: =SUM(E72:E88) -> 820853.02 | F89: =SUM(F72:F88) -> 311153.02 | G89: =SUM(G72:G88) -> 300 | H89: =SUM(H72:H88) -> 0 | I89: =SUM(I72:I88) -> 0 | J89: =SUM(J72:J88) -> 310853.02 | K89: =SUM(K72:K88) -> 0 | L89: =SUM(L72:L88) -> 0 | ... V89: =SUM(V72:V88) -> 509700
B90: Office Supplies | D90: NSTP | E90: 14405 | F90: =SUM(G90:U90) -> 0 | V90: =E90-F90 -> 14405
D91: Athletic | E91: 50000 | F91: =SUM(G91:U91) -> 0 | V91: =E91-F91 -> 50000
D92: Comp Fee/Int | F92: =SUM(G92:U92) -> 0 | V92: =E92-F92 -> 0
D93: Cultural Fees | E93: 28700 | F93: =SUM(G93:U93) -> 28700 | M93: 28700 | V93: =E93-F93 -> 0
D94: Dev Fee | F94: =SUM(G94:U94) -> 0 | V94: =E94-F94 -> 0
D95: Registrar | E95: 191965
D96: Guidance | E96: 50000 | F96: =SUM(G96:U96) -> 0 | V96: =E96-F96 -> 50000
D97: SAF | F97: =SUM(G97:U97) -> 0 | V97: =E97-F97 -> 0
D98: SCF | E98: 45610 | F98: =SUM(G98:U98) -> 45610 | J98: 45610 | V98: =E98-F98 -> 0
D99: SOF | E99: 9950 | F99: =SUM(G99:U99) -> 9950 | J99: 9950 | V99: =E99-F99 -> 0
D100: Laboratory | F100: =SUM(G100:U100) -> 0 | V100: =E100-F100 -> 0
D101: Library | F101: =SUM(G101:U101) -> 0 | V101: =E101-F101 -> 0
D102: Medical | E102: 19463 | F102: =SUM(G102:U102) -> 19463 | J102: 19463 | V102: =E102-F102 -> 0
D103: Dental | F103: =SUM(G103:U103) -> 0 | V103: =E103-F103 -> 0
D104: School ID | F104: =SUM(G104:U104) -> 0 | V104: =E104-F104 -> 0
...

Sheet CABAC Non-Fid 2025
A2: COMPARATIVE APPROVED BUDGET and ACTUAL COLLECTION
A3: INTERNALLY GENERATED FUNDS (IGF)
A4: Non-Fiduciary
A5: CY 2025 | V5: Page 1 of 3
A6: EVSU ORMOC CAMPUS
E7: Approved | H7: A L L O T M E N T
E8: Budget | G8: Total | H8: (ACTUAL COLLECTION)
A9: Particulars | E9: (Based on | F9: Programs | G9: Available | K9: FHE March 13,2025 | S9: FHE
E10: Estimated | G10: Allotment | H10: Jan | I10: Feb | J10: Mar | L10: Apr | M10: May | N10: June | O10: July | P10: August | Q10: Sep | R10: Oct | S10: SS 2023-2024 | T10: Nov | U10: Dec | V10: Balance
E11: Collection)
A12: I. Personnel Services (PS) | E12: =E21 -> 7103777.5 | F12: =F21 -> 0 | G12: =G21 -> 3509675.9 | H12: =H21 -> 0 | I12: =I21 -> 0 | J12: =J21 -> 0 | L12: =L21 -> 13224 | M12: =M21 -> 15529.75 | N12: =N21 -> 72895.88 | O12: =O21 -> 0 | P12: =P21 -> 0 | Q12: =Q21 -> 0 | R12: =R21 -> 0 | S12: =S21 -> 0 | ... V12: =V21 -> 3594101.6
A13: Honoraria | E13: 2000000 | F13: Fac & Staff Dev | G13: =SUM(H13:U13) -> 1528875 | K13: 1461851.2 | L13: 9280 | M13: 6588.75 | N13: 51155 | V13: =E13-G13 -> 471125
E14: 4487201.2 | F14: Curr Devt | G14: =SUM(H14:U14) -> 1574857.2 | K14: 1546175 | L14: 3248 | M14: 7530 | N14: 17904.25 | V14: =E14-G14 -> 2912344
E15: 16576.22 | F15: Student Dev | G15: =SUM(H15:U15) -> 5943.63 | L15: 696 | M15: 1411 | N15: 3836.63 | V15: =E15-G15 -> 10632.59
E16: 300000 | F16: Research | G16: =SUM(H16:U16) -> 200000 | K16: 200000 | V16: =E16-G16 -> 100000
E17: 300000 | F17: Extension | G17: =SUM(H17:U17) -> 200000 | K17: 200000 | V17: =E17-G17 -> 100000
F18: GS | G18: =SUM(H18:U18) -> 0 | V18: =E18-G18 -> 0
F19: Petition | G19: =SUM(H19:U19) -> 0 | V19: =E19-G19 -> 0
F20: Admin | G20: =SUM(H20:U20) -> 0 | V20: =E20-G20 -> 0
E21: =SUM(E13:E20) -> 7103777.5 | F21: =SUM(F13:F20) -> 0 | G21: =SUM(G13:G20) -> 3509675.9 | H21: =SUM(H13:H20) -> 0 | I21: =SUM(I13:I20) -> 0 | J21: =SUM(J13:J20) -> 0 | K21: =SUM(K13:K20) -> 3408026.2 | L21: =SUM(L13:L20) -> 13224 | ... V21: =SUM(V13:V20) -> 3594101.6
A22: II. Maintenance and Other Operating
A23: Expenses (MOOE) | E23: =E32+E38+E47+E50+E61+E67+E77+E79+E86+E92+E98+E100+E115+E121+E130+E132+E141+E143+E148+E155+E160+E162+E169+E177+E183+E199+E202+E215+E150+E195+E126 -> 18440309 | G23: =G32+G38+G47+G50+G61+G67+G77+G79+G86+G92+G98+G100+G115+G121+G130+G132+G141+G143+G148+G155+G160+G162+G169+G177+G183+G199+G202+G215+G150+G195+G126 -> 0 | H23: =H32+H38+H47+H50+H61+H67+H77+H79+H86+H92+H98+H100+H115+H121+H130+H132+H141+H143+H148+H155+H160+H162+H169+H177+H183+H199+H202+H215+H150+H195+H126 -> 0 | I23: =I32+I38+I47+I50+I61+I67+I77+I79+I86+I92+I98+I100+I115+I121+I130+I132+I141+I143+I148+I155+I160+I162+I169+I177+I183+I199+I202+I215+I150+I195+I126 -> 0 | J23: =J32+J38+J47+J50+J61+J67+J77+J79+J86+J92+J98+J100+J115+J121+J130+J132+J141+J143+J148+J155+J160+J162+J169+J177+J183+J199+J202+J215+J150+J195+J126 -> 0 | L23: =L32+L38+L47+L50+L61+L67+L77+L79+L86+L92+L98+L100+L115+L121+L130+L132+L141+L143+L148+L155+L160+L162+L169+L177+L183+L199+L202+L215+L150+L195+L126 -> 0 | M23: =M32+M38+M47+M50+M61+M67+M77+M79+M86+M92+M98+M100+M115+M121+M130+M132+M141+M143+M148+M155+M160+M162+M169+M177+M183+M199+M202+M215+M150+M195+M126 -> 0 | N23: =N32+N38+N47+N50+N61+N67+N77+N79+N86+N92+N98+N100+N115+N121+N130+N132+N141+N143+N148+N155+N160+N162+N169+N177+N183+N199+N202+N215+N150+N195+N126 -> 0 | O23: =O32+O38+O47+O50+O61+O67+O77+O79+O86+O92+O98+O100+O115+O121+O130+O132+O141+O143+O148+O155+O160+O162+O169+O177+O183+O199+O202+O215+O150+O195+O126 -> 0 | P23: =P32+P38+P47+P50+P61+P67+P77+P79+P86+P92+P98+P100+P115+P121+P130+P132+P141+P143+P148+P155+P160+P162+P169+P177+P183+P199+P202+P215+P150+P195+P126 -> 0 | Q23: =Q32+Q38+Q47+Q50+Q61+Q67+Q77+Q79+Q86+Q92+Q98+Q100+Q115+Q121+Q130+Q132+Q141+Q143+Q148+Q155+Q160+Q162+Q169+Q177+Q183+Q199+Q202+Q215+Q150+Q195+Q126 -> 0 | R23: =R32+R38+R47+R50+R61+R67+R77+R79+R86+R92+R98+R100+R115+R121+R130+R132+R141+R143+R148+R155+R160+R162+R169+R177+R183+R199+R202+R215+R150+R195+R126 -> 0 | S23: =S32+S38+S47+S50+S61+S67+S77+S79+S86+S92+S98+S100+S115+S121+S130+S132+S141+S143+S148+S155+S160+S162+S169+S177+S183+S199+S202+S215+S150+S195+S126 -> 0 | ... U23: =U32+U38+U47+U50+U61+U67+U77+U79+U86+U92+U98+U100+U115+U121+U130+U132+U141+U143+U148+U155+U160+U162+U169+U177+U183+U199+U202+U215+U150+U195+U126 -> 0 | V23: =E23-G23 -> 10943733 | X23: =V32+V38+V47+V50+V61+V67+V77+V79+V86+V92+V98+V100+V115+V121+V128+V132+V141+V148+V150+V155+V160+V162+V164+V169+V177+V183+V199+V202+V215 -> 9417232.2
V24: =E24-G24 -> 0
A25: Traveling Expenses - Local | E25: 500000 | F25: Fac & Staff Dev | G25: =SUM(H25:U25) -> 200000 | K25: 200000 | V25: =E25-G25 -> 300000
E26: 100000 | F26: Curr Devt | G26: =SUM(H26:U26) -> 100000 | K26: 100000 | V26: =E26-G26 -> 0
E27: 181640 | F27: Student Dev | G27: =SUM(H27:U27) -> 100000 | K27: 100000 | V27: =E27-G27 -> 81640
E28: 200000 | F28: Research | G28: =SUM(H28:U28) -> 200000 | K28: 200000 | V28: =E28-G28 -> 0
E29: 400000 | F29: Extension | G29: =SUM(H29:U29) -> 200000 | K29: 200000 | V29: =E29-G29 -> 200000
E30: 99023.88 | F30: Production | G30: =SUM(H30:U30) -> 35000 | K30: 35000 | V30: =E30-G30 -> 64023.88
E31: 400000 | F31: Admin | G31: =SUM(H31:U31) -> 155621 | K31: 150000 | L31: =1856 -> 1856 | M31: 3765 | V31: =E31-G31 -> 244379
E32: =SUM(E25:E31) -> 1880663.9 | G32: =SUM(G25:G31) -> 990621 | H32: =SUM(H25:H31) -> 0 | I32: =SUM(I25:I31) -> 0 | J32: =SUM(J25:J31) -> 0 | K32: =SUM(K25:K31) -> 985000 | L32: =SUM(L25:L31) -> 1856 | M32: =SUM(M25:M31) -> 3765 | N32: =SUM(N25:N31) -> 0 | ... V32: =SUM(V25:V31) -> 890042.88
A34: Traveling Expenses - Foreign | F34: Fac & Staff Dev | G34: =SUM(H34:U34) -> 0 | V34: =E34-G34 -> 0
F35: Curr Devt | G35: =SUM(H35:U35) -> 0 | V35: =E35-G35 -> 0
E36: 200000 | F36: Research | G36: =SUM(H36:U36) -> 103765 | K36: 100000 | M36: 3765 | V36: =E36-G36 -> 96235
F37: Extension | G37: =SUM(H37:U37) -> 0 | V37: =E37-G37 -> 0
E38: =SUM(E34:E37) -> 200000 | G38: =SUM(G34:G37) -> 103765 | H38: =SUM(H34:H37) -> 0 | I38: =SUM(I34:I37) -> 0 | J38: =SUM(J34:J37) -> 0 | K38: =SUM(K34:K37) -> 100000 | L38: =SUM(L34:L37) -> 0 | M38: =SUM(M34:M37) -> 3765 | N38: =SUM(N34:N37) -> 0 | ... V38: =SUM(V34:V37) -> 96235
A40: Training Expenses | E40: 300000 | F40: Fac & Staff Dev | G40: =SUM(H40:U40) -> 100000 | K40: 100000 | V40: =E40-G40 -> 200000
E41: 50000 | F41: Student Dev | G41: =SUM(H41:U41) -> 50000 | K41: 50000 | V41: =E41-G41 -> 0
E42: 100000 | F42: Curr Devt | G42: =SUM(H42:U42) -> 100000 | K42: 100000 | V42: =E42-G42 -> 0
E43: 350000 | F43: Research | G43: =SUM(H43:U43) -> 300000 | K43: 300000 | V43: =E43-G43 -> 50000
E44: 300000 | F44: Extension | G44: =SUM(I44:U44) -> 100000 | K44: 100000 | V44: =E44-G44 -> 200000
F45: Production | G45: =SUM(H45:U45) -> 0 | V45: =E45-G45 -> 0
E46: 200000 | F46: Admin | G46: =SUM(H46:U46) -> 50000 | K46: 50000 | V46: =E46-G46 -> 150000
E47: =SUM(E40:E46) -> 1300000 | F47: =SUM(F40:F46) -> 0 | G47: =SUM(G40:G46) -> 700000 | H47: =SUM(H40:H46) -> 0 | I47: =SUM(I40:I46) -> 0 | J47: =SUM(J40:J46) -> 0 | K47: =SUM(K40:K46) -> 700000 | L47: =SUM(L40:L46) -> 0 | ... V47: =SUM(V40:V46) -> 600000
A50: Scholarship Expenses | F50: Fac & Staff Dev | G50: =SUM(H50:U50) -> 0 | L50: 0 | V50: =E50-G50 -> 0
E51: =E50 -> 0 | G51: =G50 -> 0 | H51: =H50 -> 0 | I51: =I50 -> 0 | J51: =J50 -> 0 | K51: =K50 -> 0 | L51: =L50 -> 0 | M51: =M50 -> 0 | N51: =N50 -> 0 | ... V51: =V50 -> 0
V53: =E53-G53 -> 0
A54: Office Supplies Expenses | E54: 50000 | F54: Research | G54: =SUM(H54:U54) -> 50000 | K54: 50000 | V54: =E54-G54 -> 0
E55: 200000 | F55: Extension | G55: =SUM(H55:U55) -> 103765 | K55: 100000 | M55: 3765 | V55: =E55-G55 -> 96235
E56: 200000 | F56: Student Devt | G56: =SUM(H56:U56) -> 100000 | K56: 100000 | V56: =E56-G56 -> 100000
E57: 100000 | F57: Curr. Dev. | G57: =SUM(H57:U57) -> 100000 | K57: 100000 | V57: =E57-G57 -> 0
E58: 642291 | F58: Fac & Staff Dev | G58: =SUM(H58:U58) -> 100000 | K58: 100000 | V58: =E58-G58 -> 542291
E59: 423900 | F59: Production | G59: =SUM(H59:U59) -> 205621 | K59: 200000 | L59: 1856 | M59: 3765 | V59: =E59-G59 -> 218279
E60: 500000 | F60: Admin | G60: =SUM(H60:U60) -> 209230 | H60: 50520 | I60: 33050 | J60: 25660 | K60: 100000 | V60: =E60-G60 -> 290770
E61: =SUM(E54:E60) -> 2116191 | F61: =SUM(F54:F60) -> 0 | G61: =SUM(G54:G60) -> 868616 | H61: =SUM(H54:H60) -> 50520 | I61: =SUM(I54:I60) -> 33050 | J61: =SUM(J54:J60) -> 25660 | K61: =SUM(K54:K60) -> 750000 | U61: =SUM(U54:U60) -> 0 | V61: =SUM(V54:V60) -> 1247575
A63: Fuel, Oil and Lubricants Expenses | E63: 200000 | F63: Extension | G63: =SUM(H63:U63) -> 1856 | L63: 1856 | V63: =E63-G63 -> 198144
E64: 50000 | F64: Research | G64: =SUM(H64:U64) -> 1856 | L64: =1856 -> 1856 | V64: =E64-G64 -> 48144
F65: Facilities Dev | G65: =SUM(H65:U65) -> 0 | M65: 0 | S65: 0 | V65: =E65-G65 -> 0
E66: 100000 | F66: Admin | G66: =SUM(H66:U66) -> 50000 | K66: 50000 | M66: 0 | S66: 0 | V66: =E66-G66 -> 50000
E67: =SUM(E63:E66) -> 350000 | F67: =SUM(F63:F66) -> 0 | G67: =SUM(G63:G66) -> 53712 | H67: =SUM(H63:H66) -> 0 | I67: =SUM(I63:I66) -> 0 | J67: =SUM(J63:J66) -> 0 | K67: =SUM(K63:K66) -> 50000 | L67: =SUM(L63:L66) -> 3712 | ... V67: =SUM(V63:V66) -> 296288
A69: Other Supplies and Materials | E69: 250000 | F69: Student Devt | G69: =SUM(H69:U69) -> 100000 | K69: 100000 | V69: =E69-G69 -> 150000
F70: Facilities Dev | G70: =SUM(H70:U70) -> 0 | V70: =E70-G70 -> 0
E71: =500000+200000+200000 -> 900000 | F71: Fac & Staff Dev | G71: =SUM(H71:U71) -> 300000 | K71: 300000 | V71: =E71-G71 -> 600000
E72: =100000+150000+150000 -> 400000 | F72: Curr. Dev. | G72: =SUM(H72:U72) -> 200000 | K72: 200000 | V72: =E72-G72 -> 200000
E73: =200000+33923.88 -> 233923.88 | F73: Research | G73: =SUM(H73:U73) -> 0 | V73: =E73-G73 -> 233923.88
E74: =200000+70000+96450 -> 366450 | F74: Extension | G74: =SUM(H74:U74) -> 200000 | K74: 200000 | V74: =E74-G74 -> 166450
E75: =300000+50000+50000 -> 400000 | F75: Admin | G75: =SUM(H75:U75) -> 364425.5 | K75: 150000 | L75: 42774 | M75: 128877.5 | N75: 42774 | V75: =E75-G75 -> 35574.5
E76: =197545+50000 -> 247545 | F76: Production | G76: =SUM(H76:U76) -> 197545 | K76: 197545 | V76: =E76-G76 -> 50000
E77: =SUM(E69:E76) -> 2797918.9 | F77: =SUM(F69:F76) -> 0 | G77: =SUM(G69:G76) -> 1361970.5 | H77: =SUM(H69:H76) -> 0 | I77: =SUM(I69:I76) -> 0 | J77: =SUM(J69:J76) -> 0 | K77: =SUM(K69:K76) -> 1147545 | L77: =SUM(L69:L76) -> 42774 | ... U77: =SUM(U69:U76) -> 0 | V77: =E77-G77 -> 1435948.4
A79: Water Expenses | E79: 200000 | F79: Admin | G79: =SUM(H79:U79) -> 100000 | K79: 100000 | L79: 0 | M79: 0 | O79: 0 | V79: =E79-G79 -> 100000
E80: 150000 | F80: Extension | G80: =SUM(H80:U80) -> 50000 | K80: 50000 | V80: =E80-G80 -> 100000
E81: 400000 | F81: Facilities Dev | G81: =SUM(H81:U81) -> 0 | V81: =E81-G81 -> 400000
E82: 400000 | F82: Facilities Dev | G82: =SUM(H82:U82) -> 201624 | K82: 200000 | L82: 1624 | V82: =E82-G82 -> 198376
E83: 100000 | F83: Research | G83: =SUM(H83:U83) -> 0 | V83: =E83-G83 -> 100000
E84: =SUM(E79:E83) -> 1250000 | G84: =SUM(G79:G83) -> 351624 | H84: =SUM(H79:H83) -> 0 | I84: =SUM(I79:I83) -> 0 | J84: =SUM(J79:J83) -> 0 | K84: =SUM(K79:K83) -> 350000 | L84: =SUM(L79:L83) -> 1624 | M84: =SUM(M79:M83) -> 0 | N84: =SUM(N79:N83) -> 0 | ... V84: =SUM(V79:V83) -> 898376
A86: Electricity Expenses | E86: 200000 | F86: Admin | G86: =SUM(H86:U86) -> 133915 | H86: 0 | I86: 0 | J86: 0 | K86: 133915 | L86: 0 | M86: 0 | V86: =E86-G86 -> 66085
E87: 467983.12 | F87: Production | G87: =SUM(H87:U87) -> 351370 | K87: 351370 | V87: =E87-G87 -> 116613.12
E88: 150000 | F88: Extension | G88: =SUM(H88:U88) -> 126715 | K88: 126715 | V88: =E88-G88 -> 23285
E89: 200000 | F89: Research | G89: =SUM(H89:U89) -> 0 | V89: =E89-G89 -> 200000
E90: =SUM(E86:E89) -> 1017983.1 | G90: =SUM(G86:G89) -> 612000 | H90: =SUM(H86:H89) -> 0 | I90: =SUM(I86:I89) -> 0 | J90: =SUM(J86:J89) -> 0 | K90: =SUM(K86:K89) -> 612000 | L90: =SUM(L86:L89) -> 0 | M90: =SUM(M86:M89) -> 0 | N90: =SUM(N86:N89) -> 0 | ... V90: =SUM(V86:V89) -> 405983.12
A92: Postage and Courier Services | F92: Admin | G92: =SUM(H92:U92) -> 0 | L92: 0 | M92: 0 | V92: =E92-G92 -> 0
A93: Telephone Expenses - Mobile | E93: 200000 | F93: Admin | G93: =SUM(H93:U93) -> 200000 | K93: 200000 | V93: =E93-G93 -> 0
E94: 10800 | F94: Research | G94: =SUM(H94:U94) -> 0 | V94: =E94-G94 -> 10800
E95: 360000 | F95: Curr. Dev. | G95: =SUM(H95:U95) -> 100000 | K95: 100000 | V95: =E95-G95 -> 260000
E96: 150000 | F96: Fac & Staff Dev | G96: =SUM(H96:U96) -> 50000 | K96: 50000 | V96: =E96-G96 -> 100000
E97: 11000 | F97: Extension | G97: =SUM(H97:U97) -> 7200 | K97: 7200 | L97: 0 | M97: 0 | V97: =E97-G97 -> 3800
E98: =SUM(E93:E97) -> 731800 | F98: =SUM(F93:F97) -> 0 | G98: =SUM(G93:G97) -> 357200 | H98: =SUM(H93:H97) -> 0 | I98: =SUM(I93:I97) -> 0 | J98: =SUM(J93:J97) -> 0 | K98: =SUM(K93:K97) -> 357200 | L98: =SUM(L93:L97) -> 0 | ... V98: =SUM(V93:V97) -> 374600
A100: Cable, Sattelite Radio, Telegraph | F100: Admin | G100: =SUM(H100:U100) -> 0 | V100: =E100-G100 -> 0
A103: COMPARATIVE APPROVED BUDGET and ACTUAL COLLECTION
A104: INTERNALLY GENERATED FUNDS (IGF)
A105: Non-Fiduciary
A106: CY 2025 | V106: Page 2 of 3
A107: EVSU ORMOC CAMPUS
E108: Approved | H108: A L L O T M E N T
E109: Budget | G109: Total | H109: (ACTUAL COLLECTION)
A110: Particulars | E110: (Based on | F110: Programs | G110: Available | K110: FHE March 13,2025 | S110: FHE
E111: Estimated | G111: Allotment | H111: Jan | I111: Feb | J111: March | L111: Apr | M111: May | N111: June | O111: Jul | P111: August | Q111: Sep | R111: Oct | S111: SS 2023-2024 | T111: Nov | U111: Dec | V111: Balance
E112: Collection)
A113: Insurance Expense | F113: Admin | G113: =SUM(H113:U113) -> 0 | V113: =E113-G113 -> 0
F114: Extension | G114: =SUM(H114:U114) -> 0 | V114: =E114-G114 -> 0
...

Sheet IGF Balances Detailed 2025
A2: Internally Generated Funds (IGF)
A3: CY 2024 Detailed Balances
A5: EVSU Main Campus | V5: Page 1 of 20
A6: Particulars | E6: Beginning | F6: Approved Budget | G6: SOF | H6: BOR Res | I6: BOR Res | J6: BOR Res | K6: MAF | L6: MAF | M6: MAF | N6: BOR Res | O6: BOR Res | P6: MAF | Q6: MAF | R6: MAF | S6: MAF | U6: Actual | V6: Ending
E7: Balance | F7: (Actual Collection) | H7: 2024-095 | I7: 2025-002 | R7: INSERT | S7: INSERT | T7: Total | U7: Utilizations | V7: Balance
E8: as of | F8: CY 2025 | R8: ADJUSTMENT | S8: ADJUSTMENT | T8: Available | U8: as of | V8: as of
E9: 01/01/2025 | F9: (As of January 2025) | H9: Dated July 8, 2024 | I9: Dated March 11, 2025 | K9: 001 Dated June 27, 2025 | R9: HERE | S9: HERE | T9: Allotment | U9: December 31, 2025 | V9: =U9 -> December 31, 2025
A10: (1) | E10: (2) | F10: (3) | G10: (4.a) | H10: (4.b) | I10: (5) | J10: (4.c) | K10: (6) | L10: (4.d) | M10: (4.e) | N10: (4.f) | O10: (6) | P10: (6) | Q10: (6) | R10: (6) | S10: (6) | T10: (7)=(2)+(3)+(4)+(5)+(6) | U10: (8) | V10: (9)=(7)-(8)
A11: Personnel Services (PS)
A12: Honoraria | T12: =SUM(E12:S12) -> 0 | V12: =T12-U12 -> 0
A13: 5-01-02-100-01 | B13: Fac & Staff Dev/Curri Dev | E13: =175642.08 -> 175642.08 | F13: ='CABAC Non-Fid 2025'!G13+'CABAC Non-Fid 2025'!G14 -> 3103732.2 | I13: ='CABAC Non-Fid 2025'!K13+'CABAC Non-Fid 2025'!K14 -> 3008026.2 | T13: =SUM(E13:S13) -> 6287400.6 | V13: =T13-U13 -> 6287400.6
B14: Adv Educ | T14: =SUM(E14:S14) -> 0 | V14: =T14-U14 -> 0
B15: Research | E15: 1975445.8 | F15: ='CABAC Non-Fid 2025'!G16 -> 200000 | I15: ='CABAC Non-Fid 2025'!K16 -> 200000 | T15: =SUM(E15:S15) -> 2375445.8 | V15: =T15-U15 -> 2375445.8
B16: Extension | E16: 150000 | F16: ='CABAC Non-Fid 2025'!G17 -> 200000 | I16: ='CABAC Non-Fid 2025'!K17 -> 200000 | T16: =SUM(E16:S16) -> 550000 | V16: =T16-U16 -> 550000
B17: Student Dev Fee ( NF) | E17: 5000 | F17: ='CABAC Non-Fid 2025'!G15 -> 5943.63 | T17: =SUM(E17:S17) -> 10943.63 | V17: =T17-U17 -> 10943.63
B18: Athletic | E18: 143029.2 | F18: ='CABAC Fiduciary 2025'!F20 -> 99503.1 | I18: ='CABAC Fiduciary 2025'!J20 -> 98603.1 | T18: =SUM(E18:S18) -> 341135.4 | V18: =T18-U18 -> 341135.4
B19: Computer Fee | E19: 503376.06 | F19: ='CABAC Fiduciary 2025'!F17 -> 313585.15 | I19: ='CABAC Fiduciary 2025'!J17 -> 313585.15 | T19: =SUM(E19:S19) -> 1130546.4 | V19: =T19-U19 -> 1130546.4
B20: Laboratory Fee | F20: ='CABAC Fiduciary 2025'!F13+'CABAC Fiduciary 2025'!F15 -> 3082651 | I20: ='CABAC Fiduciary 2025'!J13+'CABAC Fiduciary 2025'!J15 -> 3082651 | T20: =SUM(E20:S20) -> 6165301.9 | V20: =T20-U20 -> 6165301.9
B21: Library | E21: 50000 | T21: =SUM(E21:S21) -> 50000 | V21: =T21-U21 -> 50000
B22: Cultural | E22: 200000 | T22: =SUM(E22:S22) -> 200000 | V22: =T22-U22 -> 200000
B23: Guidance Fee | E23: 5000 | T23: =SUM(E23:S23) -> 5000 | V23: =T23-U23 -> 5000
B24: Medical Fee | E24: 90000 | T24: =SUM(E24:S24) -> 90000 | V24: =T24-U24 -> 90000
B25: NSTP Fee | E25: 172563.74 | F25: ='CABAC Fiduciary 2025'!F19 -> 196781.93 | I25: ='CABAC Fiduciary 2025'!J19 -> 196781.93 | T25: =SUM(E25:S25) -> 566127.6 | V25: =T25-U25 -> 566127.6
B26: SCF | E26: 50000 | F26: ='CABAC Fiduciary 2025'!F32 -> 208500 | T26: =SUM(E26:S26) -> 258500 | V26: =T26-U26 -> 258500
B27: SAF | E27: 9778.91 | F27: ='CABAC Fiduciary 2025'!F31+'CABAC Non-Fid 2025'!G19 -> 186834 | T27: =SUM(E27:S27) -> 196612.91 | V27: =T27-U27 -> 196612.91
B28: School Organ Fee | E28: 30000 | T28: =SUM(E28:S28) -> 30000 | V28: =T28-U28 -> 30000
B29: Dev't Fee (F) | F29: ='CABAC Fiduciary 2025'!F16 -> 2000000 | I29: ='CABAC Fiduciary 2025'!J16 -> 2000000 | T29: =SUM(E29:S29) -> 4000000 | V29: =T29-U29 -> 4000000
B30: Sub-Total | E30: =SUM(E12:E29) -> 3559835.8 | F30: =SUM(F12:F29) -> 9597531 | G30: =SUM(G12:G29) -> 0 | H30: =SUM(H12:H29) -> 0 | I30: =SUM(I12:I29) -> 9099647.4 | J30: =SUM(J12:J29) -> 0 | K30: =SUM(K12:K29) -> 0 | L30: =SUM(L12:L29) -> 0 | ... V30: =SUM(V12:V29) -> 22257014
D31: FID | E31: =E18+E19+E20+E21+E22+E23+E24+E25+E26+E27+E28+E29 -> 1253747.9 | F31: =SUM(F18:F29) -> 6087855.2 | G31: =SUM(G18:G29) -> 0 | H31: =SUM(H18:H29) -> 0 | I31: =SUM(I18:I29) -> 5691621.2 | J31: =SUM(J18:J29) -> 0 | K31: =SUM(K18:K29) -> 0 | L31: =SUM(L18:L29) -> 0 | M31: =SUM(M18:M29) -> 0 | ... V31: =SUM(V18:V29) -> 13033224
D32: NF | E32: =E13+E14+E15+E16+E17 -> 2306087.9 | F32: =SUM(F12:F16) -> 3503732.2 | G32: =SUM(G12:G16) -> 0 | H32: =SUM(H12:H16) -> 0 | I32: =SUM(I12:I16) -> 3408026.2 | J32: =SUM(J12:J16) -> 0 | K32: =SUM(K12:K16) -> 0 | L32: =SUM(L12:L16) -> 0 | M32: =SUM(M12:M16) -> 0 | ... V32: =SUM(V12:V16) -> 9212846.4
E33: =SUM(E31:E32) -> 3559835.8 | F33: =SUM(F31:F32) -> 9591587.4 | G33: =SUM(G31:G32) -> 0 | H33: =SUM(H31:H32) -> 0 | I33: =SUM(I31:I32) -> 9099647.4 | J33: =SUM(J31:J32) -> 0 | K33: =SUM(K31:K32) -> 0 | L33: =SUM(L31:L32) -> 0 | ... V33: =SUM(V31:V32) -> 22246071
E34: =E33-E30 -> 0 | F34: =F33-F30 -> -5943.63 | G34: =G33-G30 -> 0 | H34: =H33-H30 -> 0 | I34: =I33-I30 -> 0 | J34: =J33-J30 -> 0 | K34: =K33-K30 -> 0 | L34: =L33-L30 -> 0 | ... V34: =V33-V30 -> -10943.63
A35: Total, PS | E35: =E30 -> 3559835.8 | F35: =F30 -> 9597531 | G35: =G30 -> 0 | H35: =H30 -> 0 | I35: =I30 -> 9099647.4 | J35: =J30 -> 0 | K35: =K30 -> 0 | L35: =L30 -> 0 | ... V35: =V30 -> 22257014
A38: Maintenance and Other Operating Expenses (MOOE)
A40: Travelling Expenses - | B40: GAS | T40: =SUM(E40:S40) -> 0 | V40: =T40-U40 -> 0
A41: Local | B41: Production | E41: 50000 | F41: ='CABAC Non-Fid 2025'!G30 -> 35000 | T41: =SUM(E41:S41) -> 85000 | V41: =T41-U41 -> 85000
A42: 5-02-01-010-00 | B42: Fac & Staff Dev/Curri Dev | E42: =300000+100000 -> 400000 | F42: ='CABAC Non-Fid 2025'!G25+'CABAC Non-Fid 2025'!G26 -> 300000 | T42: =SUM(E42:S42) -> 700000 | V42: =T42-U42 -> 700000
B43: Student Development - NF | E43: 200000 | F43: ='CABAC Non-Fid 2025'!G27 -> 100000 | T43: =SUM(E43:S43) -> 300000 | V43: =T43-U43 -> 300000
B44: Admin | E44: 334226.75 | F44: ='CABAC Non-Fid 2025'!G31 -> 155621 | T44: =SUM(E44:S44) -> 489847.75 | V44: =T44-U44 -> 489847.75
B45: Research | E45: 150000 | F45: ='CABAC Non-Fid 2025'!G28 -> 200000 | T45: =SUM(E45:S45) -> 350000 | V45: =T45-U45 -> 350000
B46: Extension | E46: 365773.25 | F46: ='CABAC Non-Fid 2025'!G29 -> 200000 | T46: =SUM(E46:S46) -> 565773.25 | V46: =T46-U46 -> 565773.25
B47: Athletic Fee | E47: 82888.78 | F47: ='CABAC Fiduciary 2025'!F38 -> 364436.8 | I47: ='CABAC Fiduciary 2025'!J38 -> 364436.8 | K47: 1000000 | T47: =SUM(E47:S47) -> 1811762.4 | V47: =T47-U47 -> 1811762.4
B48: Computer Fee | F48: ='CABAC Fiduciary 2025'!F40 -> 194368.72 | I48: ='CABAC Fiduciary 2025'!J40 -> 194368.72 | T48: =SUM(E48:S48) -> 388737.44 | V48: =T48-U48 -> 388737.44
B49: Cultural Fee | E49: 100000 | F49: ='CABAC Fiduciary 2025'!F41 -> 218314.54 | T49: =SUM(E49:S49) -> 318314.54 | V49: =T49-U49 -> 318314.54
B50: SCUAA | E50: 20000 | F50: ='CABAC Fiduciary 2025'!F39 -> 180876.64 | I50: ='CABAC Fiduciary 2025'!J39 -> 87996.64 | T50: =SUM(E50:S50) -> 288873.28 | V50: =T50-U50 -> 288873.28
B51: Guidance Fee | E51: 26175.3 | F51: ='CABAC Fiduciary 2025'!F49 -> 5940 | T51: =SUM(E51:S51) -> 32115.3 | V51: =T51-U51 -> 32115.3
B52: Registrar Fee | E52: 30000 | T52: =SUM(E52:S52) -> 30000 | V52: =T52-U52 -> 30000
B53: Laboratory Fee | T53: =SUM(E53:S53) -> 0 | V53: =T53-U53 -> 0
B54: Library Fee | E54: 30000 | F54: ='CABAC Fiduciary 2025'!F51 -> 50900 | I54: ='CABAC Fiduciary 2025'!J51 -> 50000 | T54: =SUM(E54:S54) -> 130900 | V54: =T54-U54 -> 130900
B55: Medical Fee | E55: 30000 | F55: ='CABAC Fiduciary 2025'!F52 -> 50600 | I55: ='CABAC Fiduciary 2025'!J52 -> 50000 | T55: =SUM(E55:S55) -> 130600 | V55: =T55-U55 -> 130600
B56: NSTP Fee | F56: ='CABAC Fiduciary 2025'!F37 -> 59000 | I56: ='CABAC Fiduciary 2025'!J37 -> 59000 | T56: =SUM(E56:S56) -> 118000 | V56: =T56-U56 -> 118000
B57: OJT Fee | T57: =SUM(E57:S57) -> 0 | V57: =T57-U57 -> 0
B58: School Organ Fee | E58: 50000 | F58: ='CABAC Fiduciary 2025'!F48 -> 73600 | I58: ='CABAC Fiduciary 2025'!J48 -> 53800 | T58: =SUM(E58:S58) -> 177400 | V58: =T58-U58 -> 177400
B59: Student Activities Fee | E59: 30000 | F59: ='CABAC Fiduciary 2025'!F45 -> 22471 | I59: ='CABAC Fiduciary 2025'!J45 -> 22471 | T59: =SUM(E59:S59) -> 74942 | V59: =T59-U59 -> 74942
B60: Student Council Fee | E60: 50000 | F60: ='CABAC Fiduciary 2025'!F46 -> 69900 | I60: ='CABAC Fiduciary 2025'!J46 -> 60000 | T60: =SUM(E60:S60) -> 179900 | V60: =T60-U60 -> 179900
B61: Development Fee | F61: ='CABAC Fiduciary 2025'!F42 -> 3000 | T61: =SUM(E61:S61) -> 3000 | V61: =T61-U61 -> 3000
B62: Sub-Total | E62: =SUM(E40:E61) -> 1949064.1 | F62: =SUM(F40:F61) -> 2284028.7 | G62: =SUM(G40:G61) -> 0 | H62: =SUM(H40:H61) -> 0 | I62: =SUM(I40:I61) -> 942073.16 | J62: =SUM(J40:J61) -> 0 | K62: =SUM(K40:K61) -> 1000000 | L62: =SUM(L40:L61) -> 0 | ... V62: =SUM(V40:V61) -> 6175165.9
D63: FID | E63: =SUM(E47:E61) -> 449064.08 | F63: =SUM(F47:F61) -> 1293407.7 | G63: =SUM(G47:G61) -> 0 | H63: =SUM(H47:H61) -> 0 | I63: =SUM(I47:I61) -> 942073.16 | J63: =SUM(J47:J61) -> 0 | K63: =SUM(K47:K61) -> 1000000 | L63: =SUM(L47:L61) -> 0 | ... V63: =SUM(V47:V61) -> 3684544.9
D64: NF | E64: =SUM(E40:E46) -> 1500000 | F64: =SUM(F40:F46) -> 990621 | G64: =SUM(G40:G46) -> 0 | H64: =SUM(H40:H46) -> 0 | I64: =SUM(I40:I46) -> 0 | J64: =SUM(J40:J46) -> 0 | K64: =SUM(K40:K46) -> 0 | L64: =SUM(L40:L46) -> 0 | ... V64: =SUM(V40:V46) -> 2490621
E65: =SUM(E63:E64) -> 1949064.1 | F65: =SUM(F63:F64) -> 2284028.7 | G65: =SUM(G63:G64) -> 0 | H65: =SUM(H63:H64) -> 0 | I65: =SUM(I63:I64) -> 942073.16 | J65: =SUM(J63:J64) -> 0 | K65: =SUM(K63:K64) -> 1000000 | L65: =SUM(L63:L64) -> 0 | ... V65: =SUM(V63:V64) -> 6175165.9
E66: =E65-E62 -> 0 | F66: =F65-F62 -> 0 | G66: =G65-G62 -> 0 | H66: =H65-H62 -> 0 | I66: =I65-I62 -> 0 | J66: =J65-J62 -> 0 | K66: =K65-K62 -> 0 | L66: =L65-L62 -> 0 | ... V66: =V65-V62 -> 0
A68: Travelling Expenses -
A69: Foreign | B69: Fac & Staff Dev/Curri Dev | F69: ='CABAC Non-Fid 2025'!G34+'CABAC Non-Fid 2025'!G35 -> 0 | T69: =SUM(E69:S69) -> 0 | V69: =T69-U69 -> 0
A70: 5-02-01-020-00 | B70: Research | E70: 217488.71 | F70: ='CABAC Non-Fid 2025'!G36 -> 103765 | T70: =SUM(E70:S70) -> 321253.71 | V70: =T70-U70 -> 321253.71
B71: Extension | F71: ='CABAC Non-Fid 2025'!G37 -> 0 | T71: =SUM(E71:S71) -> 0 | V71: =T71-U71 -> 0
B72: OJT Fee | T72: =SUM(E72:S72) -> 0 | V72: =T72-U72 -> 0
B73: Laboratory | F73: ='CABAC Fiduciary 2025'!F58 -> 0 | T73: =SUM(E73:S73) -> 0 | V73: =T73-U73 -> 0
B74: Development Fee | F74: ='CABAC Fiduciary 2025'!F57 -> 0 | T74: =SUM(E74:S74) -> 0 | V74: =T74-U74 -> 0
B75: Sub-Total | E75: =SUM(E69:E74) -> 217488.71 | F75: =SUM(F69:F74) -> 103765 | G75: =SUM(G69:G74) -> 0 | H75: =SUM(H69:H74) -> 0 | I75: =SUM(I69:I74) -> 0 | J75: =SUM(J69:J74) -> 0 | K75: =SUM(K69:K74) -> 0 | L75: =SUM(L69:L74) -> 0 | ... V75: =SUM(V69:V74) -> 321253.71
D76: FID | E76: =SUM(E72:E74) -> 0 | F76: =SUM(F72:F74) -> 0 | G76: =SUM(G72:G74) -> 0 | H76: =SUM(H72:H74) -> 0 | I76: =SUM(I72:I74) -> 0 | J76: =SUM(J72:J74) -> 0 | K76: =SUM(K72:K74) -> 0 | L76: =SUM(L72:L74) -> 0 | ... V76: =SUM(V72:V74) -> 0
D77: NF | E77: =SUM(E69:E71) -> 217488.71 | F77: =SUM(F69:F71) -> 103765 | G77: =SUM(G69:G71) -> 0 | H77: =SUM(H69:H71) -> 0 | I77: =SUM(I69:I71) -> 0 | J77: =SUM(J69:J71) -> 0 | K77: =SUM(K69:K71) -> 0 | L77: =SUM(L69:L71) -> 0 | ... V77: =SUM(V69:V71) -> 321253.71
E78: =SUM(E76:E77) -> 217488.71 | F78: =SUM(F76:F77) -> 103765 | G78: =SUM(G76:G77) -> 0 | H78: =SUM(H76:H77) -> 0 | I78: =SUM(I76:I77) -> 0 | J78: =SUM(J76:J77) -> 0 | K78: =SUM(K76:K77) -> 0 | L78: =SUM(L76:L77) -> 0 | ... V78: =SUM(V76:V77) -> 321253.71
E79: =E78-E75 -> 0 | F79: =F78-F75 -> 0 | G79: =G78-G75 -> 0 | H79: =H78-H75 -> 0 | I79: =I78-I75 -> 0 | J79: =J78-J75 -> 0 | K79: =K78-K75 -> 0 | L79: =L78-L75 -> 0 | ... V79: =V78-V75 -> 0
A81: Training Expenses | B81: Admin | E81: 237381.65 | F81: ='CABAC Non-Fid 2025'!G46 -> 50000 | T81: =SUM(E81:S81) -> 287381.65 | V81: =T81-U81 -> 287381.65
A82: 5-02-02-010-00 | B82: Production | F82: ='CABAC Non-Fid 2025'!G45 -> 0 | T82: =SUM(E82:S82) -> 0 | V82: =T82-U82 -> 0
B83: Fac & Staff Dev/Curri Dev | E83: =100000+100000 -> 200000 | F83: ='CABAC Non-Fid 2025'!G40+'CABAC Non-Fid 2025'!G42 -> 200000 | T83: =SUM(E83:S83) -> 400000 | V83: =T83-U83 -> 400000
B84: Student Development - NF | E84: 100000 | F84: ='CABAC Non-Fid 2025'!G41 -> 50000 | T84: =SUM(E84:S84) -> 150000 | V84: =T84-U84 -> 150000
B85: Research | E85: 244159.2 | F85: ='CABAC Non-Fid 2025'!G43 -> 300000 | T85: =SUM(E85:S85) -> 544159.2 | V85: =T85-U85 -> 544159.2
B86: Extension | E86: 106000 | F86: ='CABAC Non-Fid 2025'!G44 -> 100000 | T86: =SUM(E86:S86) -> 206000 | V86: =T86-U86 -> 206000
B87: Athletic Fee | E87: 200000 | F87: ='CABAC Fiduciary 2025'!F73 -> 0 | T87: =SUM(E87:S87) -> 200000 | V87: =T87-U87 -> 200000
B88: Computer Fee | E88: 70000 | F88: ='CABAC Fiduciary 2025'!F74 -> 0 | T88: =SUM(E88:S88) -> 70000 | V88: =T88-U88 -> 70000
B89: Cultural Fee | E89: 100000 | F89: ='CABAC Fiduciary 2025'!F75 -> 0 | T89: =SUM(E89:S89) -> 100000 | V89: =T89-U89 -> 100000
B90: Dental Fee | F90: ='CABAC Fiduciary 2025'!F88 -> 0 | T90: =SUM(E90:S90) -> 0 | V90: =T90-U90 -> 0
B91: Guidance Fee | E91: 70000 | F91: ='CABAC Fiduciary 2025'!F82 -> 0 | T91: =SUM(E91:S91) -> 70000 | V91: =T91-U91 -> 70000
B92: Registrar Fee | E92: 70000 | F92: ='CABAC Fiduciary 2025'!F84 -> 0 | T92: =SUM(E92:S92) -> 70000 | V92: =T92-U92 -> 70000
B93: Laboratory | F93: ='CABAC Fiduciary 2025'!F86 -> 0 | T93: =SUM(E93:S93) -> 0 | V93: =T93-U93 -> 0
B94: Library Fee | E94: 70000 | F94: ='CABAC Fiduciary 2025'!F85 -> 20000 | T94: =SUM(E94:S94) -> 90000 | V94: =T94-U94 -> 90000
B95: Medical Fee | E95: 70000 | F95: ='CABAC Fiduciary 2025'!F87 -> 30000 | T95: =SUM(E95:S95) -> 100000 | V95: =T95-U95 -> 100000
B96: NSTP Fee | E96: 70000 | F96: ='CABAC Fiduciary 2025'!F72 -> 20000 | T96: =SUM(E96:S96) -> 90000 | V96: =T96-U96 -> 90000
B97: OJT Fee | T97: =SUM(E97:S97) -> 0 | V97: =T97-U97 -> 0
B98: School Organ Fee | E98: 70000 | F98: ='CABAC Fiduciary 2025'!F83 -> 145243.02 | T98: =SUM(E98:S98) -> 215243.02 | V98: =T98-U98 -> 215243.02
B99: Student Activities Fee | E99: 70000 | F99: ='CABAC Fiduciary 2025'!F80 -> 45910 | T99: =SUM(E99:S99) -> 115910 | V99: =T99-U99 -> 115910
B100: Student Council Fee | E100: 70000 | F100: ='CABAC Fiduciary 2025'!F81 -> 50000 | T100: =SUM(E100:S100) -> 120000 | V100: =T100-U100 -> 120000
B101: Development Fee | E101: 70000 | F101: ='CABAC Fiduciary 2025'!F76 -> 0 | T101: =SUM(E101:S101) -> 70000 | V101: =T101-U101 -> 70000
B102: Sub-Total | E102: =SUM(E81:E101) -> 1887540.9 | F102: =SUM(F81:F101) -> 1011153 | G102: =SUM(G81:G101) -> 0 | H102: =SUM(H81:H101) -> 0 | I102: =SUM(I81:I101) -> 0 | J102: =SUM(J81:J101) -> 0 | K102: =SUM(K81:K101) -> 0 | L102: =SUM(L81:L101) -> 0 | ... V102: =SUM(V81:V101) -> 2898693.9
D103: FID | E103: =SUM(E87:E101) -> 1000000 | F103: =SUM(F87:F101) -> 311153.02 | G103: =SUM(G87:G101) -> 0 | H103: =SUM(H87:H101) -> 0 | I103: =SUM(I87:I101) -> 0 | J103: =SUM(J87:J101) -> 0 | K103: =SUM(K87:K101) -> 0 | L103: =SUM(L87:L101) -> 0 | ... V103: =SUM(V87:V101) -> 1311153
D104: NF | E104: =SUM(E81:E86) -> 887540.85 | F104: =SUM(F81:F86) -> 700000 | G104: =SUM(G81:G86) -> 0 | H104: =SUM(H81:H86) -> 0 | I104: =SUM(I81:I86) -> 0 | J104: =SUM(J81:J86) -> 0 | K104: =SUM(K81:K86) -> 0 | L104: =SUM(L81:L86) -> 0 | ... V104: =SUM(V81:V86) -> 1587540.9
E105: =SUM(E103:E104) -> 1887540.9 | F105: =SUM(F103:F104) -> 1011153 | G105: =SUM(G103:G104) -> 0 | H105: =SUM(H103:H104) -> 0 | I105: =SUM(I103:I104) -> 0 | J105: =SUM(J103:J104) -> 0 | K105: =SUM(K103:K104) -> 0 | L105: =SUM(L103:L104) -> 0 | ... V105: =SUM(V103:V104) -> 2898693.9
E106: =E105-E102 -> 0 | F106: =F105-F102 -> 0 | G106: =G105-G102 -> 0 | H106: =H105-H102 -> 0 | I106: =I105-I102 -> 0 | J106: =J105-J102 -> 0 | K106: =K105-K102 -> 0 | L106: =L105-L102 -> 0 | ... V106: =V105-V102 -> 0
A108: Scholarship Expenses | B108: Student Development | T108: =SUM(E108:S108) -> 0 | V108: =T108-U108 -> 0
...
